{"trial_id": "0002", "hyperparameters": {"space": [{"class_name": "Int", "config": {"name": "num_features", "default": null, "conditions": [], "min_value": 10, "max_value": 20, "step": 2, "sampling": "linear"}}, {"class_name": "Choice", "config": {"name": "optimizer", "default": "adam", "conditions": [], "values": ["adam", "rmsprop"], "ordered": false}}, {"class_name": "Choice", "config": {"name": "init_type", "default": "glorot_uniform", "conditions": [], "values": ["glorot_uniform", "he_uniform"], "ordered": false}}], "values": {"num_features": 12, "optimizer": "rmsprop", "init_type": "he_uniform", "tuner/epochs": 3, "tuner/initial_epoch": 0, "tuner/bracket": 2, "tuner/round": 0}}, "metrics": {"metrics": {"loss": {"direction": "min", "observations": [{"value": [0.12415798008441925], "step": 2}]}, "val_loss": {"direction": "min", "observations": [{"value": [0.11766306310892105], "step": 2}]}}}, "score": 0.11766306310892105, "best_step": 2, "status": "COMPLETED", "message": null}